paco/__init__.py
paco/apply.py
paco/assertions.py
paco/compose.py
paco/concurrent.py
paco/constant.py
paco/curry.py
paco/decorator.py
paco/defer.py
paco/dropwhile.py
paco/each.py
paco/every.py
paco/filter.py
paco/filterfalse.py
paco/flat_map.py
paco/gather.py
paco/generator.py
paco/interval.py
paco/map.py
paco/observer.py
paco/once.py
paco/partial.py
paco/pipe.py
paco/race.py
paco/reduce.py
paco/repeat.py
paco/run.py
paco/series.py
paco/some.py
paco/throttle.py
paco/thunk.py
paco/timeout.py
paco/times.py
paco/until.py
paco/wait.py
paco/whilst.py
paco/wraps.py
paco-0.2.3.dist-info/DESCRIPTION.rst
paco-0.2.3.dist-info/METADATA
paco-0.2.3.dist-info/RECORD
paco-0.2.3.dist-info/WHEEL
paco-0.2.3.dist-info/metadata.json
paco-0.2.3.dist-info/top_level.txt
